PyXMake/Build/Make.py
PyXMake/Build/__init__.py
PyXMake/Build/__install__.py
PyXMake/Build/cmd/windows/iniCompiler.bat
PyXMake/Build/config/.f2py_f2cmap
PyXMake/Build/config/stm_choco.ps1
PyXMake/Build/config/stm_color.py
PyXMake/Build/config/stm_conf.py
PyXMake/Build/config/stm_doc_config
PyXMake/Build/config/stm_doc_footer.html
PyXMake/Build/config/stm_docker.ps1
PyXMake/Build/config/stm_docker_ports.ps1
PyXMake/Build/config/stm_layout.html
PyXMake/Build/config/stm_logo.ico
PyXMake/Build/config/stm_logo.png
PyXMake/Build/config/stm_makefile
PyXMake/Build/config/stm_pyfilter.py
PyXMake/Build/config/stm_sphinx.sty
PyXMake/Build/config/stm_style.css
PyXMake/Tools/ErrorHandling.py
PyXMake/Tools/Utility.py
PyXMake/Tools/__init__.py
PyXMake/VTL/__init__.py
PyXMake/VTL/__install__.py
PyXMake/VTL/abaqus.py
PyXMake/VTL/api.py
PyXMake/VTL/app.py
PyXMake/VTL/archive.py
PyXMake/VTL/bundle.py
PyXMake/VTL/chocolatey.py
PyXMake/VTL/cmake.py
PyXMake/VTL/cmd/linux/stm_cara_software.sh
PyXMake/VTL/cmd/linux/stm_conda_env.sh
PyXMake/VTL/cmd/linux/stm_jenkins_job.sh
PyXMake/VTL/cmd/linux/stm_lab_image.sh
PyXMake/VTL/cmd/linux/stm_lab_pages.sh
PyXMake/VTL/cmd/windows/stm_conda.bat
PyXMake/VTL/cmd/windows/stm_lab.bat
PyXMake/VTL/cmd/windows/stm_latex.bat
PyXMake/VTL/cmd/windows/stm_make.bat
PyXMake/VTL/cmd/windows/stm_post.bat
PyXMake/VTL/cmd/windows/stm_server.bat
PyXMake/VTL/confluence.py
PyXMake/VTL/coverage.py
PyXMake/VTL/cxx.py
PyXMake/VTL/doc/index.rst
PyXMake/VTL/doc/pyx_catalog/docker-publish-image.rst
PyXMake/VTL/doc/pyx_catalog/project-archive.rst
PyXMake/VTL/doc/pyx_catalog/project-config.rst
PyXMake/VTL/doc/pyx_catalog/project-housekeeping.rst
PyXMake/VTL/doc/pyx_catalog/project-mirror.rst
PyXMake/VTL/doc/pyx_catalog/project-overleaf.rst
PyXMake/VTL/doc/pyx_catalog/project-pages.rst
PyXMake/VTL/doc/pyx_catalog/project-release.rst
PyXMake/VTL/doc/pyx_catalog/project-snapshot.rst
PyXMake/VTL/doc/pyx_catalog/project-zenodo.rst
pyx_core-1.28.0.post1.dist-info/LICENSE
pyx_core-1.28.0.post1.dist-info/METADATA
pyx_core-1.28.0.post1.dist-info/WHEEL
pyx_core-1.28.0.post1.dist-info/entry_points.txt
pyx_core-1.28.0.post1.dist-info/RECORD
